{
  "id": "0525",
  "bank": {
    "gmgoCd": "0525",
    "gmgoNm": "전택",
    "r1": "서울",
    "r2": "동대문구"
  },
  "deferredDeposit": {
    "baseDate": "2024/03/30",
    "products": [
      {
        "title": "정기예탁금",
        "entries": [
          {"duration": null, "rate": "2.50"},
          {"duration": null, "rate": "3.00"},
          {"duration": null, "rate": "3.90"},
          {"duration": null, "rate": "3.50"},
          {"duration": null, "rate": "3.50"}
        ]
      },
      {
        "title": "MG더뱅킹정기예금",
        "entries": [{"duration": 12, "rate": "3.70"}]
      }
    ]
  },
  "installmentSavings": {
    "baseDate": "2024/03/30",
    "products": [
      {
        "title": "정기적금",
        "entries": [
          {"duration": 12, "rate": "4.00"},
          {"duration": 24, "rate": "4.00"},
          {"duration": 36, "rate": "4.00"}
        ]
      },
      {
        "title": "MG New정기적금",
        "entries": [
          {"duration": 12, "rate": "2.20"},
          {"duration": 24, "rate": "2.30"},
          {"duration": 36, "rate": "2.40"}
        ]
      },
      {
        "title": "자유적립적금",
        "entries": [
          {"duration": 1, "rate": "0.00"},
          {"duration": 6, "rate": "0.00"},
          {"duration": 12, "rate": "3.50"},
          {"duration": 24, "rate": "2.00"},
          {"duration": 36, "rate": "2.00"}
        ]
      },
      {
        "title": "Smart 자유적립적금",
        "entries": [{"duration": 12, "rate": "2.10"}]
      },
      {
        "title": "MG주거래우대자유적금",
        "entries": [{"duration": 12, "rate": "2.10"}]
      },
      {
        "title": "MG더뱅킹자유적금",
        "entries": [{"duration": 12, "rate": "3.50"}]
      },
      {
        "title": "My꿈모아자유적금",
        "entries": [{"duration": 12, "rate": "2.10"}]
      }
    ]
  },
  "baseDate": "2024/03/30"
}